CHANGES.txt
MANIFEST.in
README.txt
setup.py
corejet/__init__.py
corejet.visualization.egg-info/PKG-INFO
corejet.visualization.egg-info/SOURCES.txt
corejet.visualization.egg-info/dependency_links.txt
corejet.visualization.egg-info/entry_points.txt
corejet.visualization.egg-info/namespace_packages.txt
corejet.visualization.egg-info/not-zip-safe
corejet.visualization.egg-info/requires.txt
corejet.visualization.egg-info/top_level.txt
corejet/visualization/__init__.py
corejet/visualization/generator.py
corejet/visualization/tests.py
corejet/visualization/report-template/index.html
corejet/visualization/report-template/css/Treemap.css
corejet/visualization/report-template/css/base.css
corejet/visualization/report-template/css/viz.css
corejet/visualization/report-template/js/jit-yc.js
corejet/visualization/report-template/js/jquery-min-1.5.2.js
corejet/visualization/report-template/js/viz.js
corejet/visualization/xslt/corejet-to-jit.xsl