Metadata-Version: 1.0
Name: corejet.visualization
Version: 1.0.0
Summary: Support for generating reports visualizing CoreJet test runs
Home-page: http://corejet.org
Author: Martin Aspeli
Author-email: optilude@gmail.com
License: ZPL 2.1
Keywords: corejet
Platform: UNKNOWN
Classifier: Programming Language :: Python
